bitrix24_api_client-0.1.2.dist-info/licenses/LICENSE
bitrix24_client/__init__.py
bitrix24_client/async_client.py
bitrix24_client/base_client.py
bitrix24_client/exceptions.py
bitrix24_client/sync_client.py
bitrix24_client/utils.py
bitrix24_client/interfaces/__init__.py
bitrix24_client/interfaces/response_formatter.py
bitrix24_client/interfaces/response_validator.py
bitrix24_client/interfaces/retry_strategy.py
bitrix24_client/response_formatters/__init__.py
bitrix24_client/response_formatters/default.py
bitrix24_client/retry_strategies/__init__.py
bitrix24_client/retry_strategies/exponential.py
bitrix24_client/retry_strategies/exponential_jitter.py
bitrix24_client/retry_strategies/fixed.py
bitrix24_client/retry_strategies/linear.py
bitrix24_client/retry_strategies/logarithmic.py
bitrix24_client/validators/__init__.py
bitrix24_client/validators/default_validator.py
bitrix24_api_client-0.1.2.dist-info/METADATA
bitrix24_api_client-0.1.2.dist-info/WHEEL
bitrix24_api_client-0.1.2.dist-info/top_level.txt
bitrix24_api_client-0.1.2.dist-info/RECORD
