Metadata-Version: 2.4
Name: bitrix24-api-client
Version: 0.1.2
Summary: A modern Python client for Bitrix24 REST API. Supports both synchronous and asynchronous communication.
Author-email: Temirkhan <temirhansamurhanov@gmail.com>
License: MIT
Project-URL: Homepage, https://github.com/stemirkhan/bitrix24-api-client
Project-URL: Repository, https://github.com/stemirkhan/bitrix24-api-client
Project-URL: Issues, https://github.com/stemirkhan/bitrix24-api-client/issues
Project-URL: Documentation, https://github.com/stemirkhan/bitrix24-api-client#readme
Keywords: bitrix24,bitrix,rest,crm,api,python client,httpx,requests,async,webhook
Classifier: Development Status :: 4 - Beta
Classifier: Intended Audience :: Developers
Classifier: License :: OSI Approved :: MIT License
Classifier: Programming Language :: Python :: 3
Classifier: Programming Language :: Python :: 3.9
Classifier: Programming Language :: Python :: 3.10
Classifier: Programming Language :: Python :: 3.11
Classifier: Programming Language :: Python :: 3.12
Classifier: Operating System :: OS Independent
Classifier: Topic :: Software Development :: Libraries :: Python Modules
Classifier: Framework :: AsyncIO
Requires-Python: >=3.9
License-File: LICENSE
Requires-Dist: httpx>=0.28.1
Requires-Dist: requests>=2.32.3
Provides-Extra: dev
Requires-Dist: mypy>=1.15.0; extra == "dev"
Dynamic: license-file
